neurolib_ru/__init__.py
neurolib_ru/neuro_library.py
neurolib_ru-1.0.dist-info/METADATA
neurolib_ru-1.0.dist-info/WHEEL
neurolib_ru-1.0.dist-info/top_level.txt
neurolib_ru-1.0.dist-info/RECORD
